<?xml version = '1.0' encoding = 'UTF-8'?>
<TableProxyOraclev12c class="oracle.dbtools.crest.model.design.storage.oracle.v12c.TableProxyOraclev12c" name="JOBS" directorySegmentName="seg_0" id="C99F4842-9798-217A-5AD6-26C07D2DC3FE">
<createdBy>TIEN</createdBy>
<createdTime>2024-02-22 09:04:03 UTC</createdTime>
<ownerDesignName>123</ownerDesignName>
<schemaObject>E8854726-EFFE-8FE3-DF0C-F7FCDF3665FA</schemaObject>
<logging>YES</logging>
<partitionedRowMovement>DISABLE</partitionedRowMovement>
<segment>946A9A32-61F1-8C36-8B07-D4AADF3636C8</segment>
<tableSpace>68B85CD7-BE0F-8F97-68DA-CC9DF651ABF5</tableSpace>
<temporaryChanged>false</temporaryChanged>
<accessDriverType>oracle_loader</accessDriverType>
<rejectLimit></rejectLimit>
<inMemory>NO</inMemory>
<columnProxies itemClass="oracle.dbtools.crest.model.design.storage.oracle.v12c.ColumnProxyOraclev12c">
<ColumnProxy name="MAX_SALARY" id="12B77B6F-A569-8F6D-1407-6E27B12A8626">
<createdBy>TIEN</createdBy>
<createdTime>2024-02-22 09:04:04 UTC</createdTime>
<ownerDesignName>123</ownerDesignName>
</ColumnProxy>
<ColumnProxy name="JOB_TITLE" id="AF97DDE8-142A-057F-C2F2-3E24A6C0AA2C">
<createdBy>TIEN</createdBy>
<createdTime>2024-02-22 09:04:04 UTC</createdTime>
<ownerDesignName>123</ownerDesignName>
</ColumnProxy>
<ColumnProxy name="JOB_ID" id="F990A4FC-73EC-2166-7DA0-D3818E6D9728">
<createdBy>TIEN</createdBy>
<createdTime>2024-02-22 09:04:04 UTC</createdTime>
<ownerDesignName>123</ownerDesignName>
</ColumnProxy>
<ColumnProxy name="MIN_SALARY" id="FE2E1CC9-48CD-76DA-3903-46DF7E10F34F">
<createdBy>TIEN</createdBy>
<createdTime>2024-02-22 09:04:04 UTC</createdTime>
<ownerDesignName>123</ownerDesignName>
</ColumnProxy>
</columnProxies>
<indexProxies>
<IndexProxy class="oracle.dbtools.crest.model.design.storage.oracle.v10g.IndexProxyOraclev10g" name="JOB_ID_PK" id="7041B6E7-CB02-F68A-F098-2427CCA6C243">
<createdBy>TIEN</createdBy>
<createdTime>2024-02-22 09:04:05 UTC</createdTime>
<ownerDesignName>123</ownerDesignName>
<schemaObject>E8854726-EFFE-8FE3-DF0C-F7FCDF3665FA</schemaObject>
<segment>FB03A0BF-E168-779C-BBBA-1822A4342743</segment>
<tableSpace>68B85CD7-BE0F-8F97-68DA-CC9DF651ABF5</tableSpace>
</IndexProxy>
</indexProxies>
<primaryKeys>
<PrimaryKey class="oracle.dbtools.crest.model.design.storage.oracle.v10g.PKProxyOraclev10g" name="JOB_ID_PK" id="B6A376B2-9C6A-82B8-4BFC-F63DACA64558">
<createdBy>TIEN</createdBy>
<createdTime>2024-02-22 09:04:05 UTC</createdTime>
<ownerDesignName>123</ownerDesignName>
<segment>FB03A0BF-E168-779C-BBBA-1822A4342743</segment>
<tableSpace>68B85CD7-BE0F-8F97-68DA-CC9DF651ABF5</tableSpace>
<existingIndex>7041B6E7-CB02-F68A-F098-2427CCA6C243</existingIndex>
<indexSegment>FB03A0BF-E168-779C-BBBA-1822A4342743</indexSegment>
<indexSort>SORTED</indexSort>
<usingIndex>BY INDEX NAME</usingIndex>
</PrimaryKey>
</primaryKeys>
</TableProxyOraclev12c>